molastic/__init__.py
molastic/analysis.py
molastic/core.py
molastic/java_api.py
molastic/java_json.py
molastic/painless.py
molastic/painless_parsetab.py
molastic/query_dsl.py
molastic/rest_api.py
molastic/utils.py
molastic/api/__init__.py
molastic/api/api_interface.py
molastic/api/document.py
molastic/api/index.py
molastic/api/search.py
molastic-0.2.4.dist-info/METADATA
molastic-0.2.4.dist-info/WHEEL
molastic-0.2.4.dist-info/top_level.txt
molastic-0.2.4.dist-info/RECORD
