Metadata-Version: 2.2
Name: molastic
Version: 0.2.4
Summary: Library to easymock out elasticsearch for your tests
Author-email: Brian Estrada <brianseg014@gmail.com>
Project-URL: Homepage, https://github.com/brianseg014/molastic
Requires-Python: >3.9
Requires-Dist: python-dateutil==2.8.2
Requires-Dist: requests-mock==1.9.3
Requires-Dist: Shapely==2.0.6
Requires-Dist: haversine==2.9.0
Requires-Dist: pygeohash==1.2.0
Requires-Dist: deepmerge==1.0.1
Requires-Dist: furl==2.1.3
Requires-Dist: ply==3.11
Requires-Dist: pyjnius==1.6.1
Provides-Extra: dev
Requires-Dist: pytest==7.1.2; extra == "dev"
Requires-Dist: furl==2.1.3; extra == "dev"
Requires-Dist: black==22.3.0; extra == "dev"
Requires-Dist: flake8==4.0.1; extra == "dev"
Requires-Dist: mypy==0.961; extra == "dev"
Requires-Dist: pylint==2.14.5; extra == "dev"
Requires-Dist: coverage==6.4.2; extra == "dev"
